README.md
setup.py
YsFinance/__init__.py
YsFinance/account.py
YsFinance/backtest.py
YsFinance/data_statistics.py
YsFinance/dataget.py
YsFinance/datatools.py
YsFinance/stockcalendar.py
YsFinance/utils.py
YsFinance.egg-info/PKG-INFO
YsFinance.egg-info/SOURCES.txt
YsFinance.egg-info/dependency_links.txt
YsFinance.egg-info/requires.txt
YsFinance.egg-info/top_level.txt
YsFinance/DLmodule/__init__.py
YsFinance/DLmodule/util.py
YsFinance/DLmodule/CNN/__init__.py
YsFinance/DLmodule/transformer/AL.py
YsFinance/DLmodule/transformer/CT.py
YsFinance/DLmodule/transformer/VP.py
YsFinance/DLmodule/transformer/__init__.py
YsFinance/factor/__init__.py
YsFinance/factor/analysis.py
YsFinance/factor/factor.py
YsFinance/factor/utils.py
YsFinance/factor/alphalens/__init__.py
YsFinance/factor/alphalens/_version.py
YsFinance/factor/alphalens/api.py
YsFinance/factor/alphalens/factor.py
YsFinance/factor/alphalens/make_factor_demo.py
YsFinance/factor/alphalens/performance.py
YsFinance/factor/alphalens/plotting.py
YsFinance/factor/alphalens/tears.py
YsFinance/factor/alphalens/test.py
YsFinance/factor/alphalens/utils.py
YsFinance/factor/alphalens/tests/__init__.py
YsFinance/factor/alphalens/tests/test_performance.py
YsFinance/factor/alphalens/tests/test_tears.py
YsFinance/factor/alphalens/tests/test_utils.py
YsFinance/genfactor/__init__.py
YsFinance/genfactor/cta_alpha_factor.py
YsFinance/genfactor/cta_alpha_function.py
YsFinance/genfactor/gen.py
YsFinance/genfactor/morpho_factor.py
YsFinance/resources/__init__.py
YsFinance/resources/info.derive.finance
YsFinance/resources/stock.basic
YsFinance/resources/stock.calendar